{"Timestamp":"2021-07-07T05:51:55.0390379+03:00","Level":"Warning","MessageTemplate":"No type was specified for the decimal property '{property}' on entity type '{entityType}'. This will cause values to be silently truncated if they do not fit in the default precision and scale. Explicitly specify the SQL server column type that can accommodate all the values in 'OnModelCreating' using 'HasColumnType()', specify precision and scale using 'HasPrecision()' or configure a value converter using 'HasConversion()'.","Properties":{"property":"Cost","entityType":"Product","EventId":{"Id":30000,"Name":"Microsoft.EntityFrameworkCore.Model.Validation.DecimalTypeDefaultWarning"},"SourceContext":"Microsoft.EntityFrameworkCore.Model.Validation","ActionId":"3b2a884d-43d7-45f5-aa4a-90017175e363","ActionName":"OnlineShopWebApp.Controllers.HomeController.Index (in)","RequestId":"0HMA0U8MAOUK9:00000001","RequestPath":"/","SpanId":"|a8cfe94b-454c159790aca76b.","TraceId":"a8cfe94b-454c159790aca76b","ParentId":"","MachineName":"USER-ПК","ProcessId":16792,"ThreadId":4,"ApplicationName":"Online Shop"}}
{"Timestamp":"2021-07-07T05:51:55.6520787+03:00","Level":"Information","MessageTemplate":"HTTP {RequestMethod} {RequestPath} responded {StatusCode} in {Elapsed:0.0000} ms","Properties":{"RequestMethod":"GET","RequestPath":"/","StatusCode":200,"Elapsed":921.5868,"SourceContext":"Serilog.AspNetCore.RequestLoggingMiddleware","RequestId":"0HMA0U8MAOUK9:00000001","SpanId":"|a8cfe94b-454c159790aca76b.","TraceId":"a8cfe94b-454c159790aca76b","ParentId":"","MachineName":"USER-ПК","ProcessId":16792,"ThreadId":4,"ApplicationName":"Online Shop"},"Renderings":{"Elapsed":[{"Format":"0.0000","Rendering":"921.5868"}]}}
{"Timestamp":"2021-07-07T05:51:58.0209477+03:00","Level":"Information","MessageTemplate":"HTTP {RequestMethod} {RequestPath} responded {StatusCode} in {Elapsed:0.0000} ms","Properties":{"RequestMethod":"GET","RequestPath":"/Account/Account/Login","StatusCode":200,"Elapsed":168.1502,"SourceContext":"Serilog.AspNetCore.RequestLoggingMiddleware","RequestId":"0HMA0U8MAOUK9:00000015","SpanId":"|a8cfe955-454c159790aca76b.","TraceId":"a8cfe955-454c159790aca76b","ParentId":"","MachineName":"USER-ПК","ProcessId":16792,"ThreadId":5,"ApplicationName":"Online Shop"},"Renderings":{"Elapsed":[{"Format":"0.0000","Rendering":"168.1502"}]}}
{"Timestamp":"2021-07-07T05:52:00.1679001+03:00","Level":"Information","MessageTemplate":"HTTP {RequestMethod} {RequestPath} responded {StatusCode} in {Elapsed:0.0000} ms","Properties":{"RequestMethod":"GET","RequestPath":"/Account/Account/Register","StatusCode":200,"Elapsed":70.6852,"SourceContext":"Serilog.AspNetCore.RequestLoggingMiddleware","RequestId":"0HMA0U8MAOUKA:00000001","SpanId":"|a8cfe956-454c159790aca76b.","TraceId":"a8cfe956-454c159790aca76b","ParentId":"","MachineName":"USER-ПК","ProcessId":16792,"ThreadId":8,"ApplicationName":"Online Shop"},"Renderings":{"Elapsed":[{"Format":"0.0000","Rendering":"70.6852"}]}}
{"Timestamp":"2021-07-07T05:52:36.9977893+03:00","Level":"Information","MessageTemplate":"Сообщение отправлено успешно!","Properties":{"SourceContext":"OnlineShopWebApp.Areas.Account.Models.EmailService","ActionId":"97b7fc24-2c2d-4547-9aa9-69e8c7da1e3d","ActionName":"OnlineShopWebApp.Areas.Account.Controllers.AccountController.SendMailToRegister (in)","RequestId":"0HMA0U8MAOUKC:00000001","RequestPath":"/Account/Account/SendMailToRegister","SpanId":"|a8cfe957-454c159790aca76b.","TraceId":"a8cfe957-454c159790aca76b","ParentId":"","MachineName":"USER-ПК","ProcessId":16792,"ThreadId":5,"ApplicationName":"Online Shop"}}
{"Timestamp":"2021-07-07T06:04:16.6069831+03:00","Level":"Warning","MessageTemplate":"No type was specified for the decimal property '{property}' on entity type '{entityType}'. This will cause values to be silently truncated if they do not fit in the default precision and scale. Explicitly specify the SQL server column type that can accommodate all the values in 'OnModelCreating' using 'HasColumnType()', specify precision and scale using 'HasPrecision()' or configure a value converter using 'HasConversion()'.","Properties":{"property":"Cost","entityType":"Product","EventId":{"Id":30000,"Name":"Microsoft.EntityFrameworkCore.Model.Validation.DecimalTypeDefaultWarning"},"SourceContext":"Microsoft.EntityFrameworkCore.Model.Validation","ActionId":"0c546859-3202-46ef-af7a-628665931211","ActionName":"OnlineShopWebApp.Controllers.HomeController.Index (in)","RequestId":"0HMA0UFJBMDRC:00000001","RequestPath":"/","SpanId":"|d448cedf-406c0e81ea77f2c0.","TraceId":"d448cedf-406c0e81ea77f2c0","ParentId":"","MachineName":"USER-ПК","ProcessId":18980,"ThreadId":8,"ApplicationName":"Online Shop"}}
{"Timestamp":"2021-07-07T06:04:17.2807312+03:00","Level":"Information","MessageTemplate":"HTTP {RequestMethod} {RequestPath} responded {StatusCode} in {Elapsed:0.0000} ms","Properties":{"RequestMethod":"GET","RequestPath":"/","StatusCode":200,"Elapsed":1004.363,"SourceContext":"Serilog.AspNetCore.RequestLoggingMiddleware","RequestId":"0HMA0UFJBMDRC:00000001","SpanId":"|d448cedf-406c0e81ea77f2c0.","TraceId":"d448cedf-406c0e81ea77f2c0","ParentId":"","MachineName":"USER-ПК","ProcessId":18980,"ThreadId":8,"ApplicationName":"Online Shop"},"Renderings":{"Elapsed":[{"Format":"0.0000","Rendering":"1004.3630"}]}}
{"Timestamp":"2021-07-07T06:04:20.7877646+03:00","Level":"Information","MessageTemplate":"HTTP {RequestMethod} {RequestPath} responded {StatusCode} in {Elapsed:0.0000} ms","Properties":{"RequestMethod":"GET","RequestPath":"/Account/Account/Login","StatusCode":200,"Elapsed":173.0359,"SourceContext":"Serilog.AspNetCore.RequestLoggingMiddleware","RequestId":"0HMA0UFJBMDRD:00000001","SpanId":"|d448cee9-406c0e81ea77f2c0.","TraceId":"d448cee9-406c0e81ea77f2c0","ParentId":"","MachineName":"USER-ПК","ProcessId":18980,"ThreadId":10,"ApplicationName":"Online Shop"},"Renderings":{"Elapsed":[{"Format":"0.0000","Rendering":"173.0359"}]}}
{"Timestamp":"2021-07-07T06:04:30.2525011+03:00","Level":"Information","MessageTemplate":"HTTP {RequestMethod} {RequestPath} responded {StatusCode} in {Elapsed:0.0000} ms","Properties":{"RequestMethod":"GET","RequestPath":"/Account/Account/Register","StatusCode":200,"Elapsed":87.4087,"SourceContext":"Serilog.AspNetCore.RequestLoggingMiddleware","RequestId":"0HMA0UFJBMDRF:00000001","SpanId":"|d448ceea-406c0e81ea77f2c0.","TraceId":"d448ceea-406c0e81ea77f2c0","ParentId":"","MachineName":"USER-ПК","ProcessId":18980,"ThreadId":11,"ApplicationName":"Online Shop"},"Renderings":{"Elapsed":[{"Format":"0.0000","Rendering":"87.4087"}]}}
{"Timestamp":"2021-07-07T06:04:46.0900152+03:00","Level":"Error","MessageTemplate":"Value cannot be null. (Parameter 'address')","Properties":{"SourceContext":"OnlineShopWebApp.Areas.Account.Models.EmailService","ActionId":"0edd17d2-5b5c-4e35-9b60-cd3e93ffbf51","ActionName":"OnlineShopWebApp.Areas.Account.Controllers.AccountController.Register (in)","RequestId":"0HMA0UFJBMDRG:00000001","RequestPath":"/Account/Account/Register","SpanId":"|d448ceeb-406c0e81ea77f2c0.","TraceId":"d448ceeb-406c0e81ea77f2c0","ParentId":"","MachineName":"USER-ПК","ProcessId":18980,"ThreadId":5,"ApplicationName":"Online Shop"}}
{"Timestamp":"2021-07-07T06:04:46.2108240+03:00","Level":"Information","MessageTemplate":"HTTP {RequestMethod} {RequestPath} responded {StatusCode} in {Elapsed:0.0000} ms","Properties":{"RequestMethod":"POST","RequestPath":"/Account/Account/Register","StatusCode":200,"Elapsed":386.5959,"SourceContext":"Serilog.AspNetCore.RequestLoggingMiddleware","RequestId":"0HMA0UFJBMDRG:00000001","SpanId":"|d448ceeb-406c0e81ea77f2c0.","TraceId":"d448ceeb-406c0e81ea77f2c0","ParentId":"","MachineName":"USER-ПК","ProcessId":18980,"ThreadId":5,"ApplicationName":"Online Shop"},"Renderings":{"Elapsed":[{"Format":"0.0000","Rendering":"386.5959"}]}}
{"Timestamp":"2021-07-07T06:05:25.5996970+03:00","Level":"Information","MessageTemplate":"HTTP {RequestMethod} {RequestPath} responded {StatusCode} in {Elapsed:0.0000} ms","Properties":{"RequestMethod":"GET","RequestPath":"/Account/Account/Login","StatusCode":200,"Elapsed":36.7816,"SourceContext":"Serilog.AspNetCore.RequestLoggingMiddleware","RequestId":"0HMA0UFJBMDRH:00000001","SpanId":"|d448ceec-406c0e81ea77f2c0.","TraceId":"d448ceec-406c0e81ea77f2c0","ParentId":"","MachineName":"USER-ПК","ProcessId":18980,"ThreadId":10,"ApplicationName":"Online Shop"},"Renderings":{"Elapsed":[{"Format":"0.0000","Rendering":"36.7816"}]}}
{"Timestamp":"2021-07-07T06:05:42.1969097+03:00","Level":"Information","MessageTemplate":"HTTP {RequestMethod} {RequestPath} responded {StatusCode} in {Elapsed:0.0000} ms","Properties":{"RequestMethod":"GET","RequestPath":"/Account/Account/AccountName","StatusCode":404,"Elapsed":16.7259,"SourceContext":"Serilog.AspNetCore.RequestLoggingMiddleware","RequestId":"0HMA0UFJBMDRI:00000001","SpanId":"|d448ceed-406c0e81ea77f2c0.","TraceId":"d448ceed-406c0e81ea77f2c0","ParentId":"","MachineName":"USER-ПК","ProcessId":18980,"ThreadId":23,"ApplicationName":"Online Shop"},"Renderings":{"Elapsed":[{"Format":"0.0000","Rendering":"16.7259"}]}}
{"Timestamp":"2021-07-07T06:05:44.2834865+03:00","Level":"Information","MessageTemplate":"HTTP {RequestMethod} {RequestPath} responded {StatusCode} in {Elapsed:0.0000} ms","Properties":{"RequestMethod":"GET","RequestPath":"/Account/Account/Login","StatusCode":200,"Elapsed":68.2786,"SourceContext":"Serilog.AspNetCore.RequestLoggingMiddleware","RequestId":"0HMA0UFJBMDRI:00000003","SpanId":"|d448ceee-406c0e81ea77f2c0.","TraceId":"d448ceee-406c0e81ea77f2c0","ParentId":"","MachineName":"USER-ПК","ProcessId":18980,"ThreadId":9,"ApplicationName":"Online Shop"},"Renderings":{"Elapsed":[{"Format":"0.0000","Rendering":"68.2786"}]}}
{"Timestamp":"2021-07-07T06:09:34.0747318+03:00","Level":"Warning","MessageTemplate":"No type was specified for the decimal property '{property}' on entity type '{entityType}'. This will cause values to be silently truncated if they do not fit in the default precision and scale. Explicitly specify the SQL server column type that can accommodate all the values in 'OnModelCreating' using 'HasColumnType()', specify precision and scale using 'HasPrecision()' or configure a value converter using 'HasConversion()'.","Properties":{"property":"Cost","entityType":"Product","EventId":{"Id":30000,"Name":"Microsoft.EntityFrameworkCore.Model.Validation.DecimalTypeDefaultWarning"},"SourceContext":"Microsoft.EntityFrameworkCore.Model.Validation","ActionId":"2902f4f0-d84c-4d53-8109-2bbd8a338d25","ActionName":"OnlineShopWebApp.Controllers.HomeController.Index (in)","RequestId":"0HMA0UII9KA56:00000001","RequestPath":"/","SpanId":"|80b8fc1b-4960c58e044778d2.","TraceId":"80b8fc1b-4960c58e044778d2","ParentId":"","MachineName":"USER-ПК","ProcessId":17604,"ThreadId":7,"ApplicationName":"Online Shop"}}
{"Timestamp":"2021-07-07T06:09:34.5469333+03:00","Level":"Information","MessageTemplate":"HTTP {RequestMethod} {RequestPath} responded {StatusCode} in {Elapsed:0.0000} ms","Properties":{"RequestMethod":"GET","RequestPath":"/","StatusCode":200,"Elapsed":779.4838,"SourceContext":"Serilog.AspNetCore.RequestLoggingMiddleware","RequestId":"0HMA0UII9KA56:00000001","SpanId":"|80b8fc1b-4960c58e044778d2.","TraceId":"80b8fc1b-4960c58e044778d2","ParentId":"","MachineName":"USER-ПК","ProcessId":17604,"ThreadId":7,"ApplicationName":"Online Shop"},"Renderings":{"Elapsed":[{"Format":"0.0000","Rendering":"779.4838"}]}}
{"Timestamp":"2021-07-07T06:09:37.4403653+03:00","Level":"Information","MessageTemplate":"HTTP {RequestMethod} {RequestPath} responded {StatusCode} in {Elapsed:0.0000} ms","Properties":{"RequestMethod":"GET","RequestPath":"/Account/Account/Login","StatusCode":200,"Elapsed":140.8187,"SourceContext":"Serilog.AspNetCore.RequestLoggingMiddleware","RequestId":"0HMA0UII9KA56:00000015","SpanId":"|80b8fc25-4960c58e044778d2.","TraceId":"80b8fc25-4960c58e044778d2","ParentId":"","MachineName":"USER-ПК","ProcessId":17604,"ThreadId":9,"ApplicationName":"Online Shop"},"Renderings":{"Elapsed":[{"Format":"0.0000","Rendering":"140.8187"}]}}
{"Timestamp":"2021-07-07T06:10:20.3819443+03:00","Level":"Warning","MessageTemplate":"No type was specified for the decimal property '{property}' on entity type '{entityType}'. This will cause values to be silently truncated if they do not fit in the default precision and scale. Explicitly specify the SQL server column type that can accommodate all the values in 'OnModelCreating' using 'HasColumnType()', specify precision and scale using 'HasPrecision()' or configure a value converter using 'HasConversion()'.","Properties":{"property":"Cost","entityType":"Product","EventId":{"Id":30000,"Name":"Microsoft.EntityFrameworkCore.Model.Validation.DecimalTypeDefaultWarning"},"SourceContext":"Microsoft.EntityFrameworkCore.Model.Validation","ActionId":"31ecc2ec-a9df-4257-aace-b89e36957dcc","ActionName":"OnlineShopWebApp.Controllers.HomeController.Index (in)","RequestId":"0HMA0UJ038TR6:00000001","RequestPath":"/","SpanId":"|b733439-4a670ef4e77c7804.","TraceId":"b733439-4a670ef4e77c7804","ParentId":"","MachineName":"USER-ПК","ProcessId":10532,"ThreadId":10,"ApplicationName":"Online Shop"}}
{"Timestamp":"2021-07-07T06:10:20.9653430+03:00","Level":"Information","MessageTemplate":"HTTP {RequestMethod} {RequestPath} responded {StatusCode} in {Elapsed:0.0000} ms","Properties":{"RequestMethod":"GET","RequestPath":"/","StatusCode":200,"Elapsed":889.5205,"SourceContext":"Serilog.AspNetCore.RequestLoggingMiddleware","RequestId":"0HMA0UJ038TR6:00000001","SpanId":"|b733439-4a670ef4e77c7804.","TraceId":"b733439-4a670ef4e77c7804","ParentId":"","MachineName":"USER-ПК","ProcessId":10532,"ThreadId":10,"ApplicationName":"Online Shop"},"Renderings":{"Elapsed":[{"Format":"0.0000","Rendering":"889.5205"}]}}
{"Timestamp":"2021-07-07T06:10:23.0006599+03:00","Level":"Information","MessageTemplate":"HTTP {RequestMethod} {RequestPath} responded {StatusCode} in {Elapsed:0.0000} ms","Properties":{"RequestMethod":"GET","RequestPath":"/Account/Account/Login","StatusCode":200,"Elapsed":174.4184,"SourceContext":"Serilog.AspNetCore.RequestLoggingMiddleware","RequestId":"0HMA0UJ038TR6:00000015","SpanId":"|b733443-4a670ef4e77c7804.","TraceId":"b733443-4a670ef4e77c7804","ParentId":"","MachineName":"USER-ПК","ProcessId":10532,"ThreadId":4,"ApplicationName":"Online Shop"},"Renderings":{"Elapsed":[{"Format":"0.0000","Rendering":"174.4184"}]}}
{"Timestamp":"2021-07-07T06:11:36.7066062+03:00","Level":"Warning","MessageTemplate":"No type was specified for the decimal property '{property}' on entity type '{entityType}'. This will cause values to be silently truncated if they do not fit in the default precision and scale. Explicitly specify the SQL server column type that can accommodate all the values in 'OnModelCreating' using 'HasColumnType()', specify precision and scale using 'HasPrecision()' or configure a value converter using 'HasConversion()'.","Properties":{"property":"Cost","entityType":"Product","EventId":{"Id":30000,"Name":"Microsoft.EntityFrameworkCore.Model.Validation.DecimalTypeDefaultWarning"},"SourceContext":"Microsoft.EntityFrameworkCore.Model.Validation","ActionId":"b7e029f9-bcf8-403e-9ce1-009adcbc5c90","ActionName":"OnlineShopWebApp.Controllers.HomeController.Index (in)","RequestId":"0HMA0UJMR97FU:00000001","RequestPath":"/","SpanId":"|c2a8950c-435e0c75afbf740d.","TraceId":"c2a8950c-435e0c75afbf740d","ParentId":"","MachineName":"USER-ПК","ProcessId":16972,"ThreadId":8,"ApplicationName":"Online Shop"}}
{"Timestamp":"2021-07-07T06:11:37.1570898+03:00","Level":"Information","MessageTemplate":"HTTP {RequestMethod} {RequestPath} responded {StatusCode} in {Elapsed:0.0000} ms","Properties":{"RequestMethod":"GET","RequestPath":"/","StatusCode":200,"Elapsed":740.2311,"SourceContext":"Serilog.AspNetCore.RequestLoggingMiddleware","RequestId":"0HMA0UJMR97FU:00000001","SpanId":"|c2a8950c-435e0c75afbf740d.","TraceId":"c2a8950c-435e0c75afbf740d","ParentId":"","MachineName":"USER-ПК","ProcessId":16972,"ThreadId":8,"ApplicationName":"Online Shop"},"Renderings":{"Elapsed":[{"Format":"0.0000","Rendering":"740.2311"}]}}
{"Timestamp":"2021-07-07T06:11:38.9197806+03:00","Level":"Information","MessageTemplate":"HTTP {RequestMethod} {RequestPath} responded {StatusCode} in {Elapsed:0.0000} ms","Properties":{"RequestMethod":"GET","RequestPath":"/Account/Account/Login","StatusCode":200,"Elapsed":149.7697,"SourceContext":"Serilog.AspNetCore.RequestLoggingMiddleware","RequestId":"0HMA0UJMR97FU:00000015","SpanId":"|c2a89516-435e0c75afbf740d.","TraceId":"c2a89516-435e0c75afbf740d","ParentId":"","MachineName":"USER-ПК","ProcessId":16972,"ThreadId":5,"ApplicationName":"Online Shop"},"Renderings":{"Elapsed":[{"Format":"0.0000","Rendering":"149.7697"}]}}
{"Timestamp":"2021-07-07T06:11:40.4256636+03:00","Level":"Information","MessageTemplate":"HTTP {RequestMethod} {RequestPath} responded {StatusCode} in {Elapsed:0.0000} ms","Properties":{"RequestMethod":"GET","RequestPath":"/Account/Account/Register","StatusCode":200,"Elapsed":70.5695,"SourceContext":"Serilog.AspNetCore.RequestLoggingMiddleware","RequestId":"0HMA0UJMR97FU:00000017","SpanId":"|c2a89517-435e0c75afbf740d.","TraceId":"c2a89517-435e0c75afbf740d","ParentId":"","MachineName":"USER-ПК","ProcessId":16972,"ThreadId":5,"ApplicationName":"Online Shop"},"Renderings":{"Elapsed":[{"Format":"0.0000","Rendering":"70.5695"}]}}
{"Timestamp":"2021-07-07T06:12:03.9108259+03:00","Level":"Error","MessageTemplate":"Value cannot be null. (Parameter 'address')","Properties":{"SourceContext":"OnlineShopWebApp.Areas.Account.Models.EmailService","ActionId":"25558c0c-c1bf-4268-bff2-4609f3e12ecf","ActionName":"OnlineShopWebApp.Areas.Account.Controllers.AccountController.Register (in)","RequestId":"0HMA0UJMR97G1:00000001","RequestPath":"/Account/Account/Register","SpanId":"|c2a89518-435e0c75afbf740d.","TraceId":"c2a89518-435e0c75afbf740d","ParentId":"","MachineName":"USER-ПК","ProcessId":16972,"ThreadId":8,"ApplicationName":"Online Shop"}}
{"Timestamp":"2021-07-07T06:12:04.2890068+03:00","Level":"Information","MessageTemplate":"HTTP {RequestMethod} {RequestPath} responded {StatusCode} in {Elapsed:0.0000} ms","Properties":{"RequestMethod":"POST","RequestPath":"/Account/Account/Register","StatusCode":200,"Elapsed":582.6095,"SourceContext":"Serilog.AspNetCore.RequestLoggingMiddleware","RequestId":"0HMA0UJMR97G1:00000001","SpanId":"|c2a89518-435e0c75afbf740d.","TraceId":"c2a89518-435e0c75afbf740d","ParentId":"","MachineName":"USER-ПК","ProcessId":16972,"ThreadId":8,"ApplicationName":"Online Shop"},"Renderings":{"Elapsed":[{"Format":"0.0000","Rendering":"582.6095"}]}}
{"Timestamp":"2021-07-07T06:13:09.7330542+03:00","Level":"Warning","MessageTemplate":"No type was specified for the decimal property '{property}' on entity type '{entityType}'. This will cause values to be silently truncated if they do not fit in the default precision and scale. Explicitly specify the SQL server column type that can accommodate all the values in 'OnModelCreating' using 'HasColumnType()', specify precision and scale using 'HasPrecision()' or configure a value converter using 'HasConversion()'.","Properties":{"property":"Cost","entityType":"Product","EventId":{"Id":30000,"Name":"Microsoft.EntityFrameworkCore.Model.Validation.DecimalTypeDefaultWarning"},"SourceContext":"Microsoft.EntityFrameworkCore.Model.Validation","ActionId":"490a5b3e-5c99-41e0-9134-34338d222c2f","ActionName":"OnlineShopWebApp.Controllers.HomeController.Index (in)","RequestId":"0HMA0UKIIRMUI:00000001","RequestPath":"/","SpanId":"|bf0a8e3f-4c7a594f1a59eb7d.","TraceId":"bf0a8e3f-4c7a594f1a59eb7d","ParentId":"","MachineName":"USER-ПК","ProcessId":15780,"ThreadId":8,"ApplicationName":"Online Shop"}}
{"Timestamp":"2021-07-07T06:13:10.1586742+03:00","Level":"Information","MessageTemplate":"HTTP {RequestMethod} {RequestPath} responded {StatusCode} in {Elapsed:0.0000} ms","Properties":{"RequestMethod":"GET","RequestPath":"/","StatusCode":200,"Elapsed":703.4303,"SourceContext":"Serilog.AspNetCore.RequestLoggingMiddleware","RequestId":"0HMA0UKIIRMUI:00000001","SpanId":"|bf0a8e3f-4c7a594f1a59eb7d.","TraceId":"bf0a8e3f-4c7a594f1a59eb7d","ParentId":"","MachineName":"USER-ПК","ProcessId":15780,"ThreadId":8,"ApplicationName":"Online Shop"},"Renderings":{"Elapsed":[{"Format":"0.0000","Rendering":"703.4303"}]}}
{"Timestamp":"2021-07-07T06:13:13.0646556+03:00","Level":"Information","MessageTemplate":"HTTP {RequestMethod} {RequestPath} responded {StatusCode} in {Elapsed:0.0000} ms","Properties":{"RequestMethod":"GET","RequestPath":"/Account/Account/Login","StatusCode":200,"Elapsed":156.0856,"SourceContext":"Serilog.AspNetCore.RequestLoggingMiddleware","RequestId":"0HMA0UKIIRMUI:00000015","SpanId":"|bf0a8e49-4c7a594f1a59eb7d.","TraceId":"bf0a8e49-4c7a594f1a59eb7d","ParentId":"","MachineName":"USER-ПК","ProcessId":15780,"ThreadId":10,"ApplicationName":"Online Shop"},"Renderings":{"Elapsed":[{"Format":"0.0000","Rendering":"156.0856"}]}}
{"Timestamp":"2021-07-07T06:13:43.4069165+03:00","Level":"Information","MessageTemplate":"HTTP {RequestMethod} {RequestPath} responded {StatusCode} in {Elapsed:0.0000} ms","Properties":{"RequestMethod":"GET","RequestPath":"/Account/Account/Register","StatusCode":200,"Elapsed":25562.9314,"SourceContext":"Serilog.AspNetCore.RequestLoggingMiddleware","RequestId":"0HMA0UKIIRMUK:00000001","SpanId":"|bf0a8e4a-4c7a594f1a59eb7d.","TraceId":"bf0a8e4a-4c7a594f1a59eb7d","ParentId":"","MachineName":"USER-ПК","ProcessId":15780,"ThreadId":10,"ApplicationName":"Online Shop"},"Renderings":{"Elapsed":[{"Format":"0.0000","Rendering":"25562.9314"}]}}
{"Timestamp":"2021-07-07T06:14:08.7086511+03:00","Level":"Error","MessageTemplate":"Value cannot be null. (Parameter 'address')","Properties":{"SourceContext":"OnlineShopWebApp.Areas.Account.Models.EmailService","ActionId":"f6aee5ea-bea5-40b6-99b4-86b27bc62caa","ActionName":"OnlineShopWebApp.Areas.Account.Controllers.AccountController.Register (in)","RequestId":"0HMA0UKIIRMUL:00000001","RequestPath":"/Account/Account/Register","SpanId":"|bf0a8e4b-4c7a594f1a59eb7d.","TraceId":"bf0a8e4b-4c7a594f1a59eb7d","ParentId":"","MachineName":"USER-ПК","ProcessId":15780,"ThreadId":21,"ApplicationName":"Online Shop"}}
{"Timestamp":"2021-07-07T06:14:09.1065400+03:00","Level":"Information","MessageTemplate":"HTTP {RequestMethod} {RequestPath} responded {StatusCode} in {Elapsed:0.0000} ms","Properties":{"RequestMethod":"POST","RequestPath":"/Account/Account/Register","StatusCode":200,"Elapsed":586.397,"SourceContext":"Serilog.AspNetCore.RequestLoggingMiddleware","RequestId":"0HMA0UKIIRMUL:00000001","SpanId":"|bf0a8e4b-4c7a594f1a59eb7d.","TraceId":"bf0a8e4b-4c7a594f1a59eb7d","ParentId":"","MachineName":"USER-ПК","ProcessId":15780,"ThreadId":21,"ApplicationName":"Online Shop"},"Renderings":{"Elapsed":[{"Format":"0.0000","Rendering":"586.3970"}]}}
{"Timestamp":"2021-07-07T06:24:46.4214848+03:00","Level":"Warning","MessageTemplate":"No type was specified for the decimal property '{property}' on entity type '{entityType}'. This will cause values to be silently truncated if they do not fit in the default precision and scale. Explicitly specify the SQL server column type that can accommodate all the values in 'OnModelCreating' using 'HasColumnType()', specify precision and scale using 'HasPrecision()' or configure a value converter using 'HasConversion()'.","Properties":{"property":"Cost","entityType":"Product","EventId":{"Id":30000,"Name":"Microsoft.EntityFrameworkCore.Model.Validation.DecimalTypeDefaultWarning"},"SourceContext":"Microsoft.EntityFrameworkCore.Model.Validation","ActionId":"6f9c1ee5-74c9-4e5a-adf4-faf7bd97fc9a","ActionName":"OnlineShopWebApp.Controllers.HomeController.Index (in)","RequestId":"0HMA0UR25QIAA:00000001","RequestPath":"/","SpanId":"|3d955118-449b94ffcf3e79e0.","TraceId":"3d955118-449b94ffcf3e79e0","ParentId":"","MachineName":"USER-ПК","ProcessId":7448,"ThreadId":5,"ApplicationName":"Online Shop"}}
{"Timestamp":"2021-07-07T06:24:46.9303388+03:00","Level":"Information","MessageTemplate":"HTTP {RequestMethod} {RequestPath} responded {StatusCode} in {Elapsed:0.0000} ms","Properties":{"RequestMethod":"GET","RequestPath":"/","StatusCode":200,"Elapsed":794.6276,"SourceContext":"Serilog.AspNetCore.RequestLoggingMiddleware","RequestId":"0HMA0UR25QIAA:00000001","SpanId":"|3d955118-449b94ffcf3e79e0.","TraceId":"3d955118-449b94ffcf3e79e0","ParentId":"","MachineName":"USER-ПК","ProcessId":7448,"ThreadId":5,"ApplicationName":"Online Shop"},"Renderings":{"Elapsed":[{"Format":"0.0000","Rendering":"794.6276"}]}}
{"Timestamp":"2021-07-07T06:24:49.1178860+03:00","Level":"Information","MessageTemplate":"HTTP {RequestMethod} {RequestPath} responded {StatusCode} in {Elapsed:0.0000} ms","Properties":{"RequestMethod":"GET","RequestPath":"/Account/Account/Login","StatusCode":200,"Elapsed":141.8579,"SourceContext":"Serilog.AspNetCore.RequestLoggingMiddleware","RequestId":"0HMA0UR25QIAA:00000015","SpanId":"|3d955122-449b94ffcf3e79e0.","TraceId":"3d955122-449b94ffcf3e79e0","ParentId":"","MachineName":"USER-ПК","ProcessId":7448,"ThreadId":4,"ApplicationName":"Online Shop"},"Renderings":{"Elapsed":[{"Format":"0.0000","Rendering":"141.8579"}]}}
{"Timestamp":"2021-07-07T06:24:50.7751077+03:00","Level":"Information","MessageTemplate":"HTTP {RequestMethod} {RequestPath} responded {StatusCode} in {Elapsed:0.0000} ms","Properties":{"RequestMethod":"GET","RequestPath":"/Account/Account/Register","StatusCode":200,"Elapsed":69.3774,"SourceContext":"Serilog.AspNetCore.RequestLoggingMiddleware","RequestId":"0HMA0UR25QIAC:00000001","SpanId":"|3d955123-449b94ffcf3e79e0.","TraceId":"3d955123-449b94ffcf3e79e0","ParentId":"","MachineName":"USER-ПК","ProcessId":7448,"ThreadId":8,"ApplicationName":"Online Shop"},"Renderings":{"Elapsed":[{"Format":"0.0000","Rendering":"69.3774"}]}}
{"Timestamp":"2021-07-07T06:25:22.4996995+03:00","Level":"Information","MessageTemplate":"Сообщение отправлено успешно!","Properties":{"SourceContext":"OnlineShopWebApp.Areas.Account.Models.EmailService","ActionId":"14aed954-6e62-4720-964b-77ab41106942","ActionName":"OnlineShopWebApp.Areas.Account.Controllers.AccountController.Register (in)","RequestId":"0HMA0UR25QIAD:00000001","RequestPath":"/Account/Account/Register","SpanId":"|3d955124-449b94ffcf3e79e0.","TraceId":"3d955124-449b94ffcf3e79e0","ParentId":"","MachineName":"USER-ПК","ProcessId":7448,"ThreadId":9,"ApplicationName":"Online Shop"}}
{"Timestamp":"2021-07-07T06:25:39.5879625+03:00","Level":"Information","MessageTemplate":"HTTP {RequestMethod} {RequestPath} responded {StatusCode} in {Elapsed:0.0000} ms","Properties":{"RequestMethod":"POST","RequestPath":"/Account/Account/Register","StatusCode":200,"Elapsed":29236.7915,"SourceContext":"Serilog.AspNetCore.RequestLoggingMiddleware","RequestId":"0HMA0UR25QIAD:00000001","SpanId":"|3d955124-449b94ffcf3e79e0.","TraceId":"3d955124-449b94ffcf3e79e0","ParentId":"","MachineName":"USER-ПК","ProcessId":7448,"ThreadId":9,"ApplicationName":"Online Shop"},"Renderings":{"Elapsed":[{"Format":"0.0000","Rendering":"29236.7915"}]}}
{"Timestamp":"2021-07-07T06:26:09.2099274+03:00","Level":"Information","MessageTemplate":"HTTP {RequestMethod} {RequestPath} responded {StatusCode} in {Elapsed:0.0000} ms","Properties":{"RequestMethod":"GET","RequestPath":"/Account/Account/Login","StatusCode":200,"Elapsed":43.2795,"SourceContext":"Serilog.AspNetCore.RequestLoggingMiddleware","RequestId":"0HMA0UR25QIAE:00000001","SpanId":"|3d955125-449b94ffcf3e79e0.","TraceId":"3d955125-449b94ffcf3e79e0","ParentId":"","MachineName":"USER-ПК","ProcessId":7448,"ThreadId":5,"ApplicationName":"Online Shop"},"Renderings":{"Elapsed":[{"Format":"0.0000","Rendering":"43.2795"}]}}
{"Timestamp":"2021-07-07T06:26:17.9618064+03:00","Level":"Information","MessageTemplate":"HTTP {RequestMethod} {RequestPath} responded {StatusCode} in {Elapsed:0.0000} ms","Properties":{"RequestMethod":"POST","RequestPath":"/Account/Account/Login","StatusCode":302,"Elapsed":82.28,"SourceContext":"Serilog.AspNetCore.RequestLoggingMiddleware","RequestId":"0HMA0UR25QIAF:00000001","SpanId":"|3d955126-449b94ffcf3e79e0.","TraceId":"3d955126-449b94ffcf3e79e0","ParentId":"","MachineName":"USER-ПК","ProcessId":7448,"ThreadId":4,"ApplicationName":"Online Shop"},"Renderings":{"Elapsed":[{"Format":"0.0000","Rendering":"82.2800"}]}}
{"Timestamp":"2021-07-07T06:26:18.0091468+03:00","Level":"Information","MessageTemplate":"HTTP {RequestMethod} {RequestPath} responded {StatusCode} in {Elapsed:0.0000} ms","Properties":{"RequestMethod":"GET","RequestPath":"/Home","StatusCode":200,"Elapsed":26.8353,"SourceContext":"Serilog.AspNetCore.RequestLoggingMiddleware","RequestId":"0HMA0UR25QIAF:00000003","SpanId":"|3d955127-449b94ffcf3e79e0.","TraceId":"3d955127-449b94ffcf3e79e0","ParentId":"","MachineName":"USER-ПК","ProcessId":7448,"ThreadId":4,"ApplicationName":"Online Shop"},"Renderings":{"Elapsed":[{"Format":"0.0000","Rendering":"26.8353"}]}}
{"Timestamp":"2021-07-07T06:28:04.1727137+03:00","Level":"Warning","MessageTemplate":"No type was specified for the decimal property '{property}' on entity type '{entityType}'. This will cause values to be silently truncated if they do not fit in the default precision and scale. Explicitly specify the SQL server column type that can accommodate all the values in 'OnModelCreating' using 'HasColumnType()', specify precision and scale using 'HasPrecision()' or configure a value converter using 'HasConversion()'.","Properties":{"property":"Cost","entityType":"Product","EventId":{"Id":30000,"Name":"Microsoft.EntityFrameworkCore.Model.Validation.DecimalTypeDefaultWarning"},"SourceContext":"Microsoft.EntityFrameworkCore.Model.Validation","ActionId":"252b386e-a35d-48d2-af73-9145e96c51e8","ActionName":"OnlineShopWebApp.Controllers.HomeController.Index (in)","RequestId":"0HMA0UST3EGC9:00000001","RequestPath":"/","SpanId":"|344a4ad7-4533e3bb888fc18f.","TraceId":"344a4ad7-4533e3bb888fc18f","ParentId":"","MachineName":"USER-ПК","ProcessId":22200,"ThreadId":11,"ApplicationName":"Online Shop"}}
{"Timestamp":"2021-07-07T06:28:04.6559120+03:00","Level":"Information","MessageTemplate":"HTTP {RequestMethod} {RequestPath} responded {StatusCode} in {Elapsed:0.0000} ms","Properties":{"RequestMethod":"GET","RequestPath":"/","StatusCode":200,"Elapsed":807.6249,"SourceContext":"Serilog.AspNetCore.RequestLoggingMiddleware","RequestId":"0HMA0UST3EGC9:00000001","SpanId":"|344a4ad7-4533e3bb888fc18f.","TraceId":"344a4ad7-4533e3bb888fc18f","ParentId":"","MachineName":"USER-ПК","ProcessId":22200,"ThreadId":11,"ApplicationName":"Online Shop"},"Renderings":{"Elapsed":[{"Format":"0.0000","Rendering":"807.6249"}]}}
{"Timestamp":"2021-07-07T06:28:08.9450924+03:00","Level":"Information","MessageTemplate":"HTTP {RequestMethod} {RequestPath} responded {StatusCode} in {Elapsed:0.0000} ms","Properties":{"RequestMethod":"GET","RequestPath":"/Account/Account/Login","StatusCode":200,"Elapsed":92.8807,"SourceContext":"Serilog.AspNetCore.RequestLoggingMiddleware","RequestId":"0HMA0UST3EGCA:00000001","SpanId":"|344a4ae1-4533e3bb888fc18f.","TraceId":"344a4ae1-4533e3bb888fc18f","ParentId":"","MachineName":"USER-ПК","ProcessId":22200,"ThreadId":8,"ApplicationName":"Online Shop"},"Renderings":{"Elapsed":[{"Format":"0.0000","Rendering":"92.8807"}]}}
{"Timestamp":"2021-07-07T06:29:19.9727433+03:00","Level":"Warning","MessageTemplate":"No type was specified for the decimal property '{property}' on entity type '{entityType}'. This will cause values to be silently truncated if they do not fit in the default precision and scale. Explicitly specify the SQL server column type that can accommodate all the values in 'OnModelCreating' using 'HasColumnType()', specify precision and scale using 'HasPrecision()' or configure a value converter using 'HasConversion()'.","Properties":{"property":"Cost","entityType":"Product","EventId":{"Id":30000,"Name":"Microsoft.EntityFrameworkCore.Model.Validation.DecimalTypeDefaultWarning"},"SourceContext":"Microsoft.EntityFrameworkCore.Model.Validation","ActionId":"a2cb7e1a-f6c1-465e-a137-0ce943d0a0b5","ActionName":"OnlineShopWebApp.Controllers.HomeController.Index (in)","RequestId":"0HMA0UTJN82S3:00000001","RequestPath":"/","SpanId":"|2295f674-4ab7f21a9b2ba606.","TraceId":"2295f674-4ab7f21a9b2ba606","ParentId":"","MachineName":"USER-ПК","ProcessId":10660,"ThreadId":4,"ApplicationName":"Online Shop"}}
{"Timestamp":"2021-07-07T06:29:20.4275733+03:00","Level":"Information","MessageTemplate":"HTTP {RequestMethod} {RequestPath} responded {StatusCode} in {Elapsed:0.0000} ms","Properties":{"RequestMethod":"GET","RequestPath":"/","StatusCode":200,"Elapsed":784.0798,"SourceContext":"Serilog.AspNetCore.RequestLoggingMiddleware","RequestId":"0HMA0UTJN82S3:00000001","SpanId":"|2295f674-4ab7f21a9b2ba606.","TraceId":"2295f674-4ab7f21a9b2ba606","ParentId":"","MachineName":"USER-ПК","ProcessId":10660,"ThreadId":4,"ApplicationName":"Online Shop"},"Renderings":{"Elapsed":[{"Format":"0.0000","Rendering":"784.0798"}]}}
{"Timestamp":"2021-07-07T06:29:23.1595373+03:00","Level":"Information","MessageTemplate":"HTTP {RequestMethod} {RequestPath} responded {StatusCode} in {Elapsed:0.0000} ms","Properties":{"RequestMethod":"GET","RequestPath":"/Account/Account/Login","StatusCode":200,"Elapsed":89.8586,"SourceContext":"Serilog.AspNetCore.RequestLoggingMiddleware","RequestId":"0HMA0UTJN82S3:00000015","SpanId":"|2295f67e-4ab7f21a9b2ba606.","TraceId":"2295f67e-4ab7f21a9b2ba606","ParentId":"","MachineName":"USER-ПК","ProcessId":10660,"ThreadId":8,"ApplicationName":"Online Shop"},"Renderings":{"Elapsed":[{"Format":"0.0000","Rendering":"89.8586"}]}}
{"Timestamp":"2021-07-07T06:30:32.8795672+03:00","Level":"Warning","MessageTemplate":"No type was specified for the decimal property '{property}' on entity type '{entityType}'. This will cause values to be silently truncated if they do not fit in the default precision and scale. Explicitly specify the SQL server column type that can accommodate all the values in 'OnModelCreating' using 'HasColumnType()', specify precision and scale using 'HasPrecision()' or configure a value converter using 'HasConversion()'.","Properties":{"property":"Cost","entityType":"Product","EventId":{"Id":30000,"Name":"Microsoft.EntityFrameworkCore.Model.Validation.DecimalTypeDefaultWarning"},"SourceContext":"Microsoft.EntityFrameworkCore.Model.Validation","ActionId":"763ed1f9-bc12-44f9-85fb-95be07c3c1d7","ActionName":"OnlineShopWebApp.Controllers.HomeController.Index (in)","RequestId":"0HMA0UU9E8UFA:00000001","RequestPath":"/","SpanId":"|f1d491cf-4223c70e2386b10d.","TraceId":"f1d491cf-4223c70e2386b10d","ParentId":"","MachineName":"USER-ПК","ProcessId":10112,"ThreadId":9,"ApplicationName":"Online Shop"}}
{"Timestamp":"2021-07-07T06:30:33.3205488+03:00","Level":"Information","MessageTemplate":"HTTP {RequestMethod} {RequestPath} responded {StatusCode} in {Elapsed:0.0000} ms","Properties":{"RequestMethod":"GET","RequestPath":"/","StatusCode":200,"Elapsed":779.6163,"SourceContext":"Serilog.AspNetCore.RequestLoggingMiddleware","RequestId":"0HMA0UU9E8UFA:00000001","SpanId":"|f1d491cf-4223c70e2386b10d.","TraceId":"f1d491cf-4223c70e2386b10d","ParentId":"","MachineName":"USER-ПК","ProcessId":10112,"ThreadId":9,"ApplicationName":"Online Shop"},"Renderings":{"Elapsed":[{"Format":"0.0000","Rendering":"779.6163"}]}}
{"Timestamp":"2021-07-07T06:30:36.4235961+03:00","Level":"Information","MessageTemplate":"HTTP {RequestMethod} {RequestPath} responded {StatusCode} in {Elapsed:0.0000} ms","Properties":{"RequestMethod":"GET","RequestPath":"/Account/Account/Login","StatusCode":200,"Elapsed":89.9447,"SourceContext":"Serilog.AspNetCore.RequestLoggingMiddleware","RequestId":"0HMA0UU9E8UFA:00000015","SpanId":"|f1d491d9-4223c70e2386b10d.","TraceId":"f1d491d9-4223c70e2386b10d","ParentId":"","MachineName":"USER-ПК","ProcessId":10112,"ThreadId":9,"ApplicationName":"Online Shop"},"Renderings":{"Elapsed":[{"Format":"0.0000","Rendering":"89.9447"}]}}
{"Timestamp":"2021-07-07T06:30:39.9037382+03:00","Level":"Information","MessageTemplate":"HTTP {RequestMethod} {RequestPath} responded {StatusCode} in {Elapsed:0.0000} ms","Properties":{"RequestMethod":"GET","RequestPath":"/Account/Account/Register","StatusCode":200,"Elapsed":68.5658,"SourceContext":"Serilog.AspNetCore.RequestLoggingMiddleware","RequestId":"0HMA0UU9E8UFD:00000001","SpanId":"|f1d491da-4223c70e2386b10d.","TraceId":"f1d491da-4223c70e2386b10d","ParentId":"","MachineName":"USER-ПК","ProcessId":10112,"ThreadId":7,"ApplicationName":"Online Shop"},"Renderings":{"Elapsed":[{"Format":"0.0000","Rendering":"68.5658"}]}}
{"Timestamp":"2021-07-07T06:31:09.2480838+03:00","Level":"Information","MessageTemplate":"Сообщение отправлено успешно!","Properties":{"SourceContext":"OnlineShopWebApp.Areas.Account.Models.EmailService","ActionId":"b8dc3707-6017-4310-b836-31fa26701ab8","ActionName":"OnlineShopWebApp.Areas.Account.Controllers.AccountController.Register (in)","RequestId":"0HMA0UU9E8UFE:00000001","RequestPath":"/Account/Account/Register","SpanId":"|f1d491db-4223c70e2386b10d.","TraceId":"f1d491db-4223c70e2386b10d","ParentId":"","MachineName":"USER-ПК","ProcessId":10112,"ThreadId":22,"ApplicationName":"Online Shop"}}
{"Timestamp":"2021-07-07T06:31:09.6499881+03:00","Level":"Information","MessageTemplate":"HTTP {RequestMethod} {RequestPath} responded {StatusCode} in {Elapsed:0.0000} ms","Properties":{"RequestMethod":"POST","RequestPath":"/Account/Account/Register","StatusCode":200,"Elapsed":1706.3757,"SourceContext":"Serilog.AspNetCore.RequestLoggingMiddleware","RequestId":"0HMA0UU9E8UFE:00000001","SpanId":"|f1d491db-4223c70e2386b10d.","TraceId":"f1d491db-4223c70e2386b10d","ParentId":"","MachineName":"USER-ПК","ProcessId":10112,"ThreadId":22,"ApplicationName":"Online Shop"},"Renderings":{"Elapsed":[{"Format":"0.0000","Rendering":"1706.3757"}]}}
{"Timestamp":"2021-07-07T06:33:25.0415321+03:00","Level":"Warning","MessageTemplate":"No type was specified for the decimal property '{property}' on entity type '{entityType}'. This will cause values to be silently truncated if they do not fit in the default precision and scale. Explicitly specify the SQL server column type that can accommodate all the values in 'OnModelCreating' using 'HasColumnType()', specify precision and scale using 'HasPrecision()' or configure a value converter using 'HasConversion()'.","Properties":{"property":"Cost","entityType":"Product","EventId":{"Id":30000,"Name":"Microsoft.EntityFrameworkCore.Model.Validation.DecimalTypeDefaultWarning"},"SourceContext":"Microsoft.EntityFrameworkCore.Model.Validation","ActionId":"c2e4e689-6b8c-4605-a8fa-6caa2571a036","ActionName":"OnlineShopWebApp.Controllers.HomeController.Index (in)","RequestId":"0HMA0UVSOHOF9:00000001","RequestPath":"/","SpanId":"|634705f6-42d1cccdd44f9d0e.","TraceId":"634705f6-42d1cccdd44f9d0e","ParentId":"","MachineName":"USER-ПК","ProcessId":16240,"ThreadId":8,"ApplicationName":"Online Shop"}}
{"Timestamp":"2021-07-07T06:33:25.4738754+03:00","Level":"Information","MessageTemplate":"HTTP {RequestMethod} {RequestPath} responded {StatusCode} in {Elapsed:0.0000} ms","Properties":{"RequestMethod":"GET","RequestPath":"/","StatusCode":200,"Elapsed":725.1403,"SourceContext":"Serilog.AspNetCore.RequestLoggingMiddleware","RequestId":"0HMA0UVSOHOF9:00000001","SpanId":"|634705f6-42d1cccdd44f9d0e.","TraceId":"634705f6-42d1cccdd44f9d0e","ParentId":"","MachineName":"USER-ПК","ProcessId":16240,"ThreadId":8,"ApplicationName":"Online Shop"},"Renderings":{"Elapsed":[{"Format":"0.0000","Rendering":"725.1403"}]}}
{"Timestamp":"2021-07-07T06:33:29.0671231+03:00","Level":"Information","MessageTemplate":"HTTP {RequestMethod} {RequestPath} responded {StatusCode} in {Elapsed:0.0000} ms","Properties":{"RequestMethod":"GET","RequestPath":"/Account/Account/Login","StatusCode":200,"Elapsed":141.3859,"SourceContext":"Serilog.AspNetCore.RequestLoggingMiddleware","RequestId":"0HMA0UVSOHOF9:00000015","SpanId":"|63470600-42d1cccdd44f9d0e.","TraceId":"63470600-42d1cccdd44f9d0e","ParentId":"","MachineName":"USER-ПК","ProcessId":16240,"ThreadId":11,"ApplicationName":"Online Shop"},"Renderings":{"Elapsed":[{"Format":"0.0000","Rendering":"141.3859"}]}}
{"Timestamp":"2021-07-07T06:33:32.0102999+03:00","Level":"Information","MessageTemplate":"HTTP {RequestMethod} {RequestPath} responded {StatusCode} in {Elapsed:0.0000} ms","Properties":{"RequestMethod":"GET","RequestPath":"/Account/Account/Register","StatusCode":200,"Elapsed":62.4906,"SourceContext":"Serilog.AspNetCore.RequestLoggingMiddleware","RequestId":"0HMA0UVSOHOF9:00000017","SpanId":"|63470601-42d1cccdd44f9d0e.","TraceId":"63470601-42d1cccdd44f9d0e","ParentId":"","MachineName":"USER-ПК","ProcessId":16240,"ThreadId":11,"ApplicationName":"Online Shop"},"Renderings":{"Elapsed":[{"Format":"0.0000","Rendering":"62.4906"}]}}
{"Timestamp":"2021-07-07T06:33:54.6495475+03:00","Level":"Information","MessageTemplate":"Сообщение отправлено успешно!","Properties":{"SourceContext":"OnlineShopWebApp.Areas.Account.Models.EmailService","ActionId":"fa4080fa-7fe6-4114-af8b-a8f34199fa49","ActionName":"OnlineShopWebApp.Areas.Account.Controllers.AccountController.Register (in)","RequestId":"0HMA0UVSOHOFA:00000001","RequestPath":"/Account/Account/Register","SpanId":"|63470602-42d1cccdd44f9d0e.","TraceId":"63470602-42d1cccdd44f9d0e","ParentId":"","MachineName":"USER-ПК","ProcessId":16240,"ThreadId":8,"ApplicationName":"Online Shop"}}
{"Timestamp":"2021-07-07T06:33:55.0572403+03:00","Level":"Information","MessageTemplate":"HTTP {RequestMethod} {RequestPath} responded {StatusCode} in {Elapsed:0.0000} ms","Properties":{"RequestMethod":"POST","RequestPath":"/Account/Account/Register","StatusCode":200,"Elapsed":1656.775,"SourceContext":"Serilog.AspNetCore.RequestLoggingMiddleware","RequestId":"0HMA0UVSOHOFA:00000001","SpanId":"|63470602-42d1cccdd44f9d0e.","TraceId":"63470602-42d1cccdd44f9d0e","ParentId":"","MachineName":"USER-ПК","ProcessId":16240,"ThreadId":8,"ApplicationName":"Online Shop"},"Renderings":{"Elapsed":[{"Format":"0.0000","Rendering":"1656.7750"}]}}
{"Timestamp":"2021-07-07T06:36:19.3592522+03:00","Level":"Warning","MessageTemplate":"No type was specified for the decimal property '{property}' on entity type '{entityType}'. This will cause values to be silently truncated if they do not fit in the default precision and scale. Explicitly specify the SQL server column type that can accommodate all the values in 'OnModelCreating' using 'HasColumnType()', specify precision and scale using 'HasPrecision()' or configure a value converter using 'HasConversion()'.","Properties":{"property":"Cost","entityType":"Product","EventId":{"Id":30000,"Name":"Microsoft.EntityFrameworkCore.Model.Validation.DecimalTypeDefaultWarning"},"SourceContext":"Microsoft.EntityFrameworkCore.Model.Validation","ActionId":"36e83c48-08a6-4d49-a601-43580141c182","ActionName":"OnlineShopWebApp.Controllers.HomeController.Index (in)","RequestId":"0HMA0V1GLTIHV:00000001","RequestPath":"/","SpanId":"|ccf7fb21-41e9a6ff0857ca88.","TraceId":"ccf7fb21-41e9a6ff0857ca88","ParentId":"","MachineName":"USER-ПК","ProcessId":7576,"ThreadId":4,"ApplicationName":"Online Shop"}}
{"Timestamp":"2021-07-07T06:36:19.8580013+03:00","Level":"Information","MessageTemplate":"HTTP {RequestMethod} {RequestPath} responded {StatusCode} in {Elapsed:0.0000} ms","Properties":{"RequestMethod":"GET","RequestPath":"/","StatusCode":200,"Elapsed":794.7325,"SourceContext":"Serilog.AspNetCore.RequestLoggingMiddleware","RequestId":"0HMA0V1GLTIHV:00000001","SpanId":"|ccf7fb21-41e9a6ff0857ca88.","TraceId":"ccf7fb21-41e9a6ff0857ca88","ParentId":"","MachineName":"USER-ПК","ProcessId":7576,"ThreadId":4,"ApplicationName":"Online Shop"},"Renderings":{"Elapsed":[{"Format":"0.0000","Rendering":"794.7325"}]}}
{"Timestamp":"2021-07-07T06:36:22.2465681+03:00","Level":"Information","MessageTemplate":"HTTP {RequestMethod} {RequestPath} responded {StatusCode} in {Elapsed:0.0000} ms","Properties":{"RequestMethod":"GET","RequestPath":"/Account/Account/Login","StatusCode":200,"Elapsed":133.8289,"SourceContext":"Serilog.AspNetCore.RequestLoggingMiddleware","RequestId":"0HMA0V1GLTIHV:00000015","SpanId":"|ccf7fb2b-41e9a6ff0857ca88.","TraceId":"ccf7fb2b-41e9a6ff0857ca88","ParentId":"","MachineName":"USER-ПК","ProcessId":7576,"ThreadId":9,"ApplicationName":"Online Shop"},"Renderings":{"Elapsed":[{"Format":"0.0000","Rendering":"133.8289"}]}}
{"Timestamp":"2021-07-07T06:36:24.7431627+03:00","Level":"Information","MessageTemplate":"HTTP {RequestMethod} {RequestPath} responded {StatusCode} in {Elapsed:0.0000} ms","Properties":{"RequestMethod":"GET","RequestPath":"/Account/Account/Register","StatusCode":200,"Elapsed":61.738,"SourceContext":"Serilog.AspNetCore.RequestLoggingMiddleware","RequestId":"0HMA0V1GLTII1:00000001","SpanId":"|ccf7fb2c-41e9a6ff0857ca88.","TraceId":"ccf7fb2c-41e9a6ff0857ca88","ParentId":"","MachineName":"USER-ПК","ProcessId":7576,"ThreadId":16,"ApplicationName":"Online Shop"},"Renderings":{"Elapsed":[{"Format":"0.0000","Rendering":"61.7380"}]}}
{"Timestamp":"2021-07-07T06:36:50.9252203+03:00","Level":"Information","MessageTemplate":"Сообщение отправлено успешно!","Properties":{"SourceContext":"OnlineShopWebApp.Areas.Account.Models.EmailService","ActionId":"d6f142eb-c0fc-4933-a977-eebb6b9413bf","ActionName":"OnlineShopWebApp.Areas.Account.Controllers.AccountController.Register (in)","RequestId":"0HMA0V1GLTII2:00000001","RequestPath":"/Account/Account/Register","SpanId":"|ccf7fb2d-41e9a6ff0857ca88.","TraceId":"ccf7fb2d-41e9a6ff0857ca88","ParentId":"","MachineName":"USER-ПК","ProcessId":7576,"ThreadId":4,"ApplicationName":"Online Shop"}}
{"Timestamp":"2021-07-07T06:36:51.0502498+03:00","Level":"Information","MessageTemplate":"HTTP {RequestMethod} {RequestPath} responded {StatusCode} in {Elapsed:0.0000} ms","Properties":{"RequestMethod":"POST","RequestPath":"/Account/Account/Register","StatusCode":200,"Elapsed":1435.0546,"SourceContext":"Serilog.AspNetCore.RequestLoggingMiddleware","RequestId":"0HMA0V1GLTII2:00000001","SpanId":"|ccf7fb2d-41e9a6ff0857ca88.","TraceId":"ccf7fb2d-41e9a6ff0857ca88","ParentId":"","MachineName":"USER-ПК","ProcessId":7576,"ThreadId":4,"ApplicationName":"Online Shop"},"Renderings":{"Elapsed":[{"Format":"0.0000","Rendering":"1435.0546"}]}}
{"Timestamp":"2021-07-07T06:50:39.1184368+03:00","Level":"Warning","MessageTemplate":"No type was specified for the decimal property '{property}' on entity type '{entityType}'. This will cause values to be silently truncated if they do not fit in the default precision and scale. Explicitly specify the SQL server column type that can accommodate all the values in 'OnModelCreating' using 'HasColumnType()', specify precision and scale using 'HasPrecision()' or configure a value converter using 'HasConversion()'.","Properties":{"property":"Cost","entityType":"Product","EventId":{"Id":30000,"Name":"Microsoft.EntityFrameworkCore.Model.Validation.DecimalTypeDefaultWarning"},"SourceContext":"Microsoft.EntityFrameworkCore.Model.Validation","ActionId":"5bac305c-f4c0-4052-a12b-65187019ee85","ActionName":"OnlineShopWebApp.Controllers.HomeController.Index (in)","RequestId":"0HMA0V9GTMDKQ:00000001","RequestPath":"/","SpanId":"|c341128d-429ac212c7a3f696.","TraceId":"c341128d-429ac212c7a3f696","ParentId":"","MachineName":"USER-ПК","ProcessId":18052,"ThreadId":7,"ApplicationName":"Online Shop"}}
{"Timestamp":"2021-07-07T06:50:39.5356198+03:00","Level":"Information","MessageTemplate":"HTTP {RequestMethod} {RequestPath} responded {StatusCode} in {Elapsed:0.0000} ms","Properties":{"RequestMethod":"GET","RequestPath":"/","StatusCode":200,"Elapsed":691.8925,"SourceContext":"Serilog.AspNetCore.RequestLoggingMiddleware","RequestId":"0HMA0V9GTMDKQ:00000001","SpanId":"|c341128d-429ac212c7a3f696.","TraceId":"c341128d-429ac212c7a3f696","ParentId":"","MachineName":"USER-ПК","ProcessId":18052,"ThreadId":7,"ApplicationName":"Online Shop"},"Renderings":{"Elapsed":[{"Format":"0.0000","Rendering":"691.8925"}]}}
{"Timestamp":"2021-07-07T06:50:42.4196554+03:00","Level":"Information","MessageTemplate":"HTTP {RequestMethod} {RequestPath} responded {StatusCode} in {Elapsed:0.0000} ms","Properties":{"RequestMethod":"GET","RequestPath":"/Account/Account/Login","StatusCode":200,"Elapsed":139.7016,"SourceContext":"Serilog.AspNetCore.RequestLoggingMiddleware","RequestId":"0HMA0V9GTMDKQ:00000015","SpanId":"|c3411297-429ac212c7a3f696.","TraceId":"c3411297-429ac212c7a3f696","ParentId":"","MachineName":"USER-ПК","ProcessId":18052,"ThreadId":11,"ApplicationName":"Online Shop"},"Renderings":{"Elapsed":[{"Format":"0.0000","Rendering":"139.7016"}]}}
{"Timestamp":"2021-07-07T06:50:45.1422233+03:00","Level":"Information","MessageTemplate":"HTTP {RequestMethod} {RequestPath} responded {StatusCode} in {Elapsed:0.0000} ms","Properties":{"RequestMethod":"GET","RequestPath":"/Account/Account/AccountName","StatusCode":404,"Elapsed":7.337,"SourceContext":"Serilog.AspNetCore.RequestLoggingMiddleware","RequestId":"0HMA0V9GTMDKR:00000001","SpanId":"|c3411298-429ac212c7a3f696.","TraceId":"c3411298-429ac212c7a3f696","ParentId":"","MachineName":"USER-ПК","ProcessId":18052,"ThreadId":4,"ApplicationName":"Online Shop"},"Renderings":{"Elapsed":[{"Format":"0.0000","Rendering":"7.3370"}]}}
{"Timestamp":"2021-07-07T06:50:51.8758304+03:00","Level":"Information","MessageTemplate":"HTTP {RequestMethod} {RequestPath} responded {StatusCode} in {Elapsed:0.0000} ms","Properties":{"RequestMethod":"GET","RequestPath":"/Account/Account/Login","StatusCode":200,"Elapsed":34.437,"SourceContext":"Serilog.AspNetCore.RequestLoggingMiddleware","RequestId":"0HMA0V9GTMDKR:00000003","SpanId":"|c3411299-429ac212c7a3f696.","TraceId":"c3411299-429ac212c7a3f696","ParentId":"","MachineName":"USER-ПК","ProcessId":18052,"ThreadId":7,"ApplicationName":"Online Shop"},"Renderings":{"Elapsed":[{"Format":"0.0000","Rendering":"34.4370"}]}}
{"Timestamp":"2021-07-07T06:52:12.3526674+03:00","Level":"Warning","MessageTemplate":"No type was specified for the decimal property '{property}' on entity type '{entityType}'. This will cause values to be silently truncated if they do not fit in the default precision and scale. Explicitly specify the SQL server column type that can accommodate all the values in 'OnModelCreating' using 'HasColumnType()', specify precision and scale using 'HasPrecision()' or configure a value converter using 'HasConversion()'.","Properties":{"property":"Cost","entityType":"Product","EventId":{"Id":30000,"Name":"Microsoft.EntityFrameworkCore.Model.Validation.DecimalTypeDefaultWarning"},"SourceContext":"Microsoft.EntityFrameworkCore.Model.Validation","ActionId":"30770dd5-fafc-43cb-aba9-363870a7c8c3","ActionName":"OnlineShopWebApp.Controllers.HomeController.Index (in)","RequestId":"0HMA0VACN57RO:00000001","RequestPath":"/","SpanId":"|ad08b4ac-487faf654f6e295e.","TraceId":"ad08b4ac-487faf654f6e295e","ParentId":"","MachineName":"USER-ПК","ProcessId":20200,"ThreadId":8,"ApplicationName":"Online Shop"}}
{"Timestamp":"2021-07-07T06:52:12.7828786+03:00","Level":"Information","MessageTemplate":"HTTP {RequestMethod} {RequestPath} responded {StatusCode} in {Elapsed:0.0000} ms","Properties":{"RequestMethod":"GET","RequestPath":"/","StatusCode":200,"Elapsed":700.0819,"SourceContext":"Serilog.AspNetCore.RequestLoggingMiddleware","RequestId":"0HMA0VACN57RO:00000001","SpanId":"|ad08b4ac-487faf654f6e295e.","TraceId":"ad08b4ac-487faf654f6e295e","ParentId":"","MachineName":"USER-ПК","ProcessId":20200,"ThreadId":8,"ApplicationName":"Online Shop"},"Renderings":{"Elapsed":[{"Format":"0.0000","Rendering":"700.0819"}]}}
{"Timestamp":"2021-07-07T06:52:15.3907017+03:00","Level":"Information","MessageTemplate":"HTTP {RequestMethod} {RequestPath} responded {StatusCode} in {Elapsed:0.0000} ms","Properties":{"RequestMethod":"GET","RequestPath":"/Account/Account/Login","StatusCode":200,"Elapsed":135.0225,"SourceContext":"Serilog.AspNetCore.RequestLoggingMiddleware","RequestId":"0HMA0VACN57RO:00000015","SpanId":"|ad08b4b6-487faf654f6e295e.","TraceId":"ad08b4b6-487faf654f6e295e","ParentId":"","MachineName":"USER-ПК","ProcessId":20200,"ThreadId":16,"ApplicationName":"Online Shop"},"Renderings":{"Elapsed":[{"Format":"0.0000","Rendering":"135.0225"}]}}
{"Timestamp":"2021-07-07T06:52:17.0273938+03:00","Level":"Information","MessageTemplate":"HTTP {RequestMethod} {RequestPath} responded {StatusCode} in {Elapsed:0.0000} ms","Properties":{"RequestMethod":"GET","RequestPath":"/Account/Account/AccountName","StatusCode":404,"Elapsed":9.0307,"SourceContext":"Serilog.AspNetCore.RequestLoggingMiddleware","RequestId":"0HMA0VACN57RP:00000001","SpanId":"|ad08b4b7-487faf654f6e295e.","TraceId":"ad08b4b7-487faf654f6e295e","ParentId":"","MachineName":"USER-ПК","ProcessId":20200,"ThreadId":8,"ApplicationName":"Online Shop"},"Renderings":{"Elapsed":[{"Format":"0.0000","Rendering":"9.0307"}]}}
{"Timestamp":"2021-07-07T06:52:30.0836937+03:00","Level":"Information","MessageTemplate":"HTTP {RequestMethod} {RequestPath} responded {StatusCode} in {Elapsed:0.0000} ms","Properties":{"RequestMethod":"GET","RequestPath":"/Account/AccountName","StatusCode":404,"Elapsed":1.0044,"SourceContext":"Serilog.AspNetCore.RequestLoggingMiddleware","RequestId":"0HMA0VACN57RR:00000001","SpanId":"|ad08b4b8-487faf654f6e295e.","TraceId":"ad08b4b8-487faf654f6e295e","ParentId":"","MachineName":"USER-ПК","ProcessId":20200,"ThreadId":4,"ApplicationName":"Online Shop"},"Renderings":{"Elapsed":[{"Format":"0.0000","Rendering":"1.0044"}]}}
{"Timestamp":"2021-07-07T07:05:28.9745295+03:00","Level":"Warning","MessageTemplate":"No type was specified for the decimal property '{property}' on entity type '{entityType}'. This will cause values to be silently truncated if they do not fit in the default precision and scale. Explicitly specify the SQL server column type that can accommodate all the values in 'OnModelCreating' using 'HasColumnType()', specify precision and scale using 'HasPrecision()' or configure a value converter using 'HasConversion()'.","Properties":{"property":"Cost","entityType":"Product","EventId":{"Id":30000,"Name":"Microsoft.EntityFrameworkCore.Model.Validation.DecimalTypeDefaultWarning"},"SourceContext":"Microsoft.EntityFrameworkCore.Model.Validation","ActionId":"0f55ea6d-fedc-413e-9138-c1f30eea048a","ActionName":"OnlineShopWebApp.Controllers.HomeController.Index (in)","RequestId":"0HMA0VHQ4ON9N:00000001","RequestPath":"/","SpanId":"|80d20bfa-4cf055a719e0d19e.","TraceId":"80d20bfa-4cf055a719e0d19e","ParentId":"","MachineName":"USER-ПК","ProcessId":9288,"ThreadId":8,"ApplicationName":"Online Shop"}}
{"Timestamp":"2021-07-07T07:05:29.4786053+03:00","Level":"Information","MessageTemplate":"HTTP {RequestMethod} {RequestPath} responded {StatusCode} in {Elapsed:0.0000} ms","Properties":{"RequestMethod":"GET","RequestPath":"/","StatusCode":200,"Elapsed":779.6489,"SourceContext":"Serilog.AspNetCore.RequestLoggingMiddleware","RequestId":"0HMA0VHQ4ON9N:00000001","SpanId":"|80d20bfa-4cf055a719e0d19e.","TraceId":"80d20bfa-4cf055a719e0d19e","ParentId":"","MachineName":"USER-ПК","ProcessId":9288,"ThreadId":8,"ApplicationName":"Online Shop"},"Renderings":{"Elapsed":[{"Format":"0.0000","Rendering":"779.6489"}]}}
{"Timestamp":"2021-07-07T07:05:32.2234249+03:00","Level":"Information","MessageTemplate":"HTTP {RequestMethod} {RequestPath} responded {StatusCode} in {Elapsed:0.0000} ms","Properties":{"RequestMethod":"GET","RequestPath":"/Account/Account/Login","StatusCode":200,"Elapsed":149.706,"SourceContext":"Serilog.AspNetCore.RequestLoggingMiddleware","RequestId":"0HMA0VHQ4ON9N:00000015","SpanId":"|80d20c04-4cf055a719e0d19e.","TraceId":"80d20c04-4cf055a719e0d19e","ParentId":"","MachineName":"USER-ПК","ProcessId":9288,"ThreadId":11,"ApplicationName":"Online Shop"},"Renderings":{"Elapsed":[{"Format":"0.0000","Rendering":"149.7060"}]}}
{"Timestamp":"2021-07-07T07:05:33.5356681+03:00","Level":"Information","MessageTemplate":"HTTP {RequestMethod} {RequestPath} responded {StatusCode} in {Elapsed:0.0000} ms","Properties":{"RequestMethod":"GET","RequestPath":"/Admin/User/ChangePassword","StatusCode":302,"Elapsed":15.1066,"SourceContext":"Serilog.AspNetCore.RequestLoggingMiddleware","RequestId":"0HMA0VHQ4ON9P:00000001","SpanId":"|80d20c05-4cf055a719e0d19e.","TraceId":"80d20c05-4cf055a719e0d19e","ParentId":"","MachineName":"USER-ПК","ProcessId":9288,"ThreadId":7,"ApplicationName":"Online Shop"},"Renderings":{"Elapsed":[{"Format":"0.0000","Rendering":"15.1066"}]}}
{"Timestamp":"2021-07-07T07:05:33.5860684+03:00","Level":"Information","MessageTemplate":"HTTP {RequestMethod} {RequestPath} responded {StatusCode} in {Elapsed:0.0000} ms","Properties":{"RequestMethod":"GET","RequestPath":"/Account/Account/Login?ReturnUrl=%2FAdmin%2FUser%2FChangePassword","StatusCode":200,"Elapsed":33.4392,"SourceContext":"Serilog.AspNetCore.RequestLoggingMiddleware","RequestId":"0HMA0VHQ4ON9P:00000003","SpanId":"|80d20c06-4cf055a719e0d19e.","TraceId":"80d20c06-4cf055a719e0d19e","ParentId":"","MachineName":"USER-ПК","ProcessId":9288,"ThreadId":4,"ApplicationName":"Online Shop"},"Renderings":{"Elapsed":[{"Format":"0.0000","Rendering":"33.4392"}]}}
{"Timestamp":"2021-07-07T07:05:40.8194694+03:00","Level":"Information","MessageTemplate":"HTTP {RequestMethod} {RequestPath} responded {StatusCode} in {Elapsed:0.0000} ms","Properties":{"RequestMethod":"GET","RequestPath":"/Admin/User/ChangePassword","StatusCode":302,"Elapsed":5.3611,"SourceContext":"Serilog.AspNetCore.RequestLoggingMiddleware","RequestId":"0HMA0VHQ4ON9P:00000005","SpanId":"|80d20c07-4cf055a719e0d19e.","TraceId":"80d20c07-4cf055a719e0d19e","ParentId":"","MachineName":"USER-ПК","ProcessId":9288,"ThreadId":9,"ApplicationName":"Online Shop"},"Renderings":{"Elapsed":[{"Format":"0.0000","Rendering":"5.3611"}]}}
{"Timestamp":"2021-07-07T07:05:40.8819662+03:00","Level":"Information","MessageTemplate":"HTTP {RequestMethod} {RequestPath} responded {StatusCode} in {Elapsed:0.0000} ms","Properties":{"RequestMethod":"GET","RequestPath":"/Account/Account/Login?ReturnUrl=%2FAdmin%2FUser%2FChangePassword","StatusCode":200,"Elapsed":43.0099,"SourceContext":"Serilog.AspNetCore.RequestLoggingMiddleware","RequestId":"0HMA0VHQ4ON9P:00000007","SpanId":"|80d20c08-4cf055a719e0d19e.","TraceId":"80d20c08-4cf055a719e0d19e","ParentId":"","MachineName":"USER-ПК","ProcessId":9288,"ThreadId":4,"ApplicationName":"Online Shop"},"Renderings":{"Elapsed":[{"Format":"0.0000","Rendering":"43.0099"}]}}
{"Timestamp":"2021-07-07T07:05:47.4929017+03:00","Level":"Information","MessageTemplate":"HTTP {RequestMethod} {RequestPath} responded {StatusCode} in {Elapsed:0.0000} ms","Properties":{"RequestMethod":"GET","RequestPath":"/Admin/User/ChangePassword","StatusCode":302,"Elapsed":3.0928,"SourceContext":"Serilog.AspNetCore.RequestLoggingMiddleware","RequestId":"0HMA0VHQ4ON9Q:00000001","SpanId":"|80d20c09-4cf055a719e0d19e.","TraceId":"80d20c09-4cf055a719e0d19e","ParentId":"","MachineName":"USER-ПК","ProcessId":9288,"ThreadId":11,"ApplicationName":"Online Shop"},"Renderings":{"Elapsed":[{"Format":"0.0000","Rendering":"3.0928"}]}}
{"Timestamp":"2021-07-07T07:05:47.5271772+03:00","Level":"Information","MessageTemplate":"HTTP {RequestMethod} {RequestPath} responded {StatusCode} in {Elapsed:0.0000} ms","Properties":{"RequestMethod":"GET","RequestPath":"/Account/Account/Login?ReturnUrl=%2FAdmin%2FUser%2FChangePassword","StatusCode":200,"Elapsed":19.9377,"SourceContext":"Serilog.AspNetCore.RequestLoggingMiddleware","RequestId":"0HMA0VHQ4ON9Q:00000003","SpanId":"|80d20c0a-4cf055a719e0d19e.","TraceId":"80d20c0a-4cf055a719e0d19e","ParentId":"","MachineName":"USER-ПК","ProcessId":9288,"ThreadId":8,"ApplicationName":"Online Shop"},"Renderings":{"Elapsed":[{"Format":"0.0000","Rendering":"19.9377"}]}}
{"Timestamp":"2021-07-07T07:06:18.0861169+03:00","Level":"Information","MessageTemplate":"HTTP {RequestMethod} {RequestPath} responded {StatusCode} in {Elapsed:0.0000} ms","Properties":{"RequestMethod":"GET","RequestPath":"/Admin/User/ChangePassword","StatusCode":302,"Elapsed":1.189,"SourceContext":"Serilog.AspNetCore.RequestLoggingMiddleware","RequestId":"0HMA0VHQ4ON9R:00000001","SpanId":"|80d20c0b-4cf055a719e0d19e.","TraceId":"80d20c0b-4cf055a719e0d19e","ParentId":"","MachineName":"USER-ПК","ProcessId":9288,"ThreadId":4,"ApplicationName":"Online Shop"},"Renderings":{"Elapsed":[{"Format":"0.0000","Rendering":"1.1890"}]}}
{"Timestamp":"2021-07-07T07:06:18.1375507+03:00","Level":"Information","MessageTemplate":"HTTP {RequestMethod} {RequestPath} responded {StatusCode} in {Elapsed:0.0000} ms","Properties":{"RequestMethod":"GET","RequestPath":"/Account/Account/Login?ReturnUrl=%2FAdmin%2FUser%2FChangePassword","StatusCode":200,"Elapsed":33.8377,"SourceContext":"Serilog.AspNetCore.RequestLoggingMiddleware","RequestId":"0HMA0VHQ4ON9R:00000003","SpanId":"|80d20c0c-4cf055a719e0d19e.","TraceId":"80d20c0c-4cf055a719e0d19e","ParentId":"","MachineName":"USER-ПК","ProcessId":9288,"ThreadId":19,"ApplicationName":"Online Shop"},"Renderings":{"Elapsed":[{"Format":"0.0000","Rendering":"33.8377"}]}}
